klassez/Spectra.py
klassez/__init__.py
klassez/anal.py
klassez/config.py
klassez/figures.py
klassez/fit.py
klassez/misc.py
klassez/processing.py
klassez/sim.py
klassez/tables/gamma.dic
klassez/tables/nuclei_jeol.dic
klassez-0.5a2.dist-info/licenses/LICENSE.txt
klassez-0.5a2.dist-info/METADATA
klassez-0.5a2.dist-info/WHEEL
klassez-0.5a2.dist-info/top_level.txt
klassez-0.5a2.dist-info/RECORD
