Metadata-Version: 2.4
Name: klassez
Version: 0.5a2
Summary: A collection of functions for NMR data handling.
Home-page: https://github.com/MetallerTM/klassez
Author: Francesco Bruno, Letizia Fiorucci
Author-email: bruno@cerm.unifi.it
License: LICENSE.txt
Classifier: Programming Language :: Python :: 3
Classifier: Operating System :: OS Independent
Classifier: License :: OSI Approved :: MIT License
Requires-Python: >=3.9
License-File: LICENSE.txt
Requires-Dist: numpy
Requires-Dist: scipy
Requires-Dist: lmfit
Requires-Dist: seaborn
Requires-Dist: nmrglue
Requires-Dist: matplotlib>=3.8
Requires-Dist: csaps
Provides-Extra: jeolproc
Requires-Dist: jeol_parser; extra == "jeolproc"
Dynamic: author
Dynamic: author-email
Dynamic: classifier
Dynamic: description
Dynamic: description-content-type
Dynamic: home-page
Dynamic: license
Dynamic: license-file
Dynamic: provides-extra
Dynamic: requires-dist
Dynamic: requires-python
Dynamic: summary
